flet_material/__init__.py
flet_material/admonition.py
flet_material/alert.py
flet_material/annotation.py
flet_material/badge.py
flet_material/base.py
flet_material/button.py
flet_material/checkbox.py
flet_material/chip.py
flet_material/switch.py
styles/__init__.py
styles/admonition_style.py
styles/alert_style.py
styles/badge_style.py
styles/fonts.py
styles/theme.py
flet_material-0.3.3.dist-info/LICENSE
flet_material-0.3.3.dist-info/METADATA
flet_material-0.3.3.dist-info/WHEEL
flet_material-0.3.3.dist-info/entry_points.txt
flet_material-0.3.3.dist-info/top_level.txt
flet_material-0.3.3.dist-info/RECORD
