Metadata-Version: 2.1
Name: flet-material
Version: 0.3.3
Summary: Material UI Library for Flet
Home-page: https://github.com/LineIndent/material_design_flet
Author: S. Ahmad P. Hakimi
Author-email: pourhakimi@pm.me
Keywords: material design,UI library,Flet
Classifier: Programming Language :: Python :: 3
Classifier: License :: OSI Approved :: MIT License
Classifier: Operating System :: OS Independent
License-File: LICENSE
Requires-Dist: click (>=8.1.3)
Requires-Dist: flet (>=0.8.1)
